npzigzag
