Metadata-Version: 2.1
Name: npzigzag
Version: 0.3
Summary: Vanilla numpy implementation of zigzag indicator.
Home-page: https://github.com/julianvanmeggelen/npzigzag
Author: Julian van Meggelen
Author-email: julianvanmeggelen@icloud.com
License: MIT
Download-URL: https://github.com/julianvanmeggelen/npzigzag/archive/refs/tags/v01.tar.gz
Keywords: zigzag,zigzag indicator
Platform: UNKNOWN
Classifier: Development Status :: 3 - Alpha
Classifier: Intended Audience :: Developers
Classifier: Topic :: Software Development :: Build Tools
Classifier: License :: OSI Approved :: MIT License
Classifier: Programming Language :: Python :: 3
Classifier: Programming Language :: Python :: 3.4
Classifier: Programming Language :: Python :: 3.5
Classifier: Programming Language :: Python :: 3.6
